CMakeLists.txt
Makefile
README
mainpage.dox
manifest.xml
setup.py
cgi-bin/gen_rosinstall.py
scripts/generate_devel.py
scripts/generate_postrelease.py
scripts/generate_prerelease.py
scripts/generate_rosinstall.py
scripts/generate_unreleased.py
scripts/run_auto_stack_devel.py
scripts/run_auto_stack_postrelease.py
scripts/run_auto_stack_prerelease.py
scripts/run_auto_stack_unreleased.py
src/job_generation/__init__.py
src/job_generation/apt_parser.py
src/job_generation/jobs_common.py
src/ros_job_generation.egg-info/PKG-INFO
src/ros_job_generation.egg-info/SOURCES.txt
src/ros_job_generation.egg-info/dependency_links.txt
src/ros_job_generation.egg-info/requires.txt
src/ros_job_generation.egg-info/top_level.txt
website/cgi-bin/gen_rosinstall.py
website/cgi-bin/prerelease_hook
website/cgi-bin/prerelease_hook_github_setup.txt
website/cgi-bin/prerelease_kickoff.py
website/html/index.html
website/html/search.png